{
  "project_info": {
    "project_number": "216551021171",
    "project_id": "shepherd-fx",
    "storage_bucket": "shepherd-fx.appspot.com"
  },
  "client": [
    {
      "client_info": {
        "mobilesdk_app_id": "1:216551021171:android:0f56cd2100fd9a3107e806",
        "android_client_info": {
          "package_name": "com.example.mailing"
        }
      },
      "oauth_client": [
        {
          "client_id": "216551021171-6uiqq1ob0m0ir656s34gmh5te8o5gmvh.apps.googleusercontent.com",
          "client_type": 3
        }
      ],
      "api_key": [
        {
          "current_key": "AIzaSyBGsOuVVio1nYAfoLL25LuYAX8n-JZ_r_I"
        }
      ],
      "services": {
        "appinvite_service": {
          "other_platform_oauth_client": [
            {
              "client_id": "216551021171-6uiqq1ob0m0ir656s34gmh5te8o5gmvh.apps.googleusercontent.com",
              "client_type": 3
            }
          ]
        }
      }
    }
  ],
  "configuration_version": "1"
}